{
  "project_info": {
    "project_number": "777477635970",
    "firebase_url": "https://saba-customer-4c05c.firebaseio.com",
    "project_id": "saba-customer-4c05c",
    "storage_bucket": "saba-customer-4c05c.appspot.com"
  },
  "client": [
    {
      "client_info": {
        "mobilesdk_app_id": "1:777477635970:android:aa6fd63378db17f5",
        "android_client_info": {
          "package_name": "com.sabaindomedika.stscustomer"
        }
      },
      "oauth_client": [
        {
          "client_id": "777477635970-uvio8inrqr0dhpes7vpefqnjs9jn7li6.apps.googleusercontent.com",
          "client_type": 1,
          "android_info": {
            "package_name": "com.sabaindomedika.stscustomer",
            "certificate_hash": "a4604cd674f3e587563bf5b1a1f65c66d59748b9"
          }
        },
        {
          "client_id": "777477635970-2lt203h2m2jb4h0o0q9ovpmf523privl.apps.googleusercontent.com",
          "client_type": 3
        }
      ],
      "api_key": [
        {
          "current_key": "AIzaSyDioR0_Ow6PjtA-_kHz8AzFkymfUW11ne0"
        }
      ],
      "services": {
        "analytics_service": {
          "status": 1
        },
        "appinvite_service": {
          "status": 2,
          "other_platform_oauth_client": [
            {
              "client_id": "777477635970-2lt203h2m2jb4h0o0q9ovpmf523privl.apps.googleusercontent.com",
              "client_type": 3
            }
          ]
        },
        "ads_service": {
          "status": 2
        }
      }
    }
  ],
  "configuration_version": "1"
}